aist/__init__.py
aist/aist.py
aist/download.py
aist/msg.py
aist/pic.py
aist-0.2.3.dist-info/METADATA
aist-0.2.3.dist-info/RECORD
aist-0.2.3.dist-info/WHEEL
aist-0.2.3.dist-info/top_level.txt
